pygrc/__init__.py
pygrc/fit.py
pygrc/plot.py
pygrc/reader.py
pygrc-0.3.0.dist-info/LICENSE
pygrc-0.3.0.dist-info/METADATA
pygrc-0.3.0.dist-info/WHEEL
pygrc-0.3.0.dist-info/top_level.txt
pygrc-0.3.0.dist-info/RECORD
